{
  "data": {
    "event": {
      "id": "112449598160932318",
      "type": "match",
      "tournament": {
        "id": "112449498998017060"
      },
      "league": {
        "id": "98767991314006698",
        "slug": "lpl",
        "image": "http://static.lolesports.com/leagues/1592516115322_LPL-01-FullonDark.png",
        "name": "LPL"
      },
      "match": {
        "strategy": {
          "count": 3
        },
        "teams": [
          {
            "id": "101388912911039804",
            "name": "THUNDER TALK GAMING",
            "code": "TT",
            "image": "http://static.lolesports.com/teams/TT-FullonDark.png",
            "result": {
              "gameWins": 2
            }
          },
          {
            "id": "99566404845279652",
            "name": "Oh My God",
            "code": "OMG",
            "image": "http://static.lolesports.com/teams/1686821355861_OMG_2023_logo-01.png",
            "result": {
              "gameWins": 0
            }
          }
        ],
        "games": [
          {
            "number": 1,
            "id": "112449598160932319",
            "state": "completed",
            "teams": [
              {
                "id": "101388912911039804",
                "side": "blue"
              },
              {
                "id": "99566404845279652",
                "side": "red"
              }
            ],
            "vods": []
          },
          {
            "number": 2,
            "id": "112449598160932320",
            "state": "completed",
            "teams": [
              {
                "id": "99566404845279652",
                "side": "blue"
              },
              {
                "id": "101388912911039804",
                "side": "red"
              }
            ],
            "vods": []
          },
          {
            "number": 3,
            "id": "112449598160932321",
            "state": "unneeded",
            "teams": [
              {
                "id": "101388912911039804",
                "side": "blue"
              },
              {
                "id": "99566404845279652",
                "side": "red"
              }
            ],
            "vods": []
          }
        ]
      },
      "streams": []
    }
  }
}